{
"skeleton": {
	"hash": "hMYVju9JvsefiigHsQJhm0XN80k",
	"spine": "3.8.97",
	"x": -909,
	"y": -542,
	"width": 1833,
	"height": 1082,
	"images": "./images/",
	"audio": "C:/Users/Евгения/Desktop/rap/scena"
},
"bones": [
	{ "name": "root" },
	{ "name": "sound1", "parent": "root", "length": 376.52, "rotation": 91.97, "x": -725.2, "y": -536.35 },
	{ "name": "sound2", "parent": "root", "length": 399.97, "rotation": 89.44, "x": 761.33, "y": -536.7 },
	{ "name": "light2", "parent": "root", "length": 99.36, "rotation": -63.08, "x": -825.17, "y": 334.71 },
	{ "name": "sv6", "parent": "light2", "length": 540.51, "rotation": -10.81, "x": 105.42, "y": -6.13 },
	{ "name": "light3", "parent": "root", "length": 105.06, "rotation": -44.47, "x": -600.27, "y": 450.57 },
	{ "name": "sv7", "parent": "light3", "length": 557.17, "rotation": -21.72, "x": 113.69, "y": -4.9 },
	{ "name": "light1", "parent": "root", "length": 70.12, "rotation": -90, "x": -294.41, "y": 535.21 },
	{ "name": "sv5", "parent": "light1", "length": 605.94, "rotation": -1.41, "x": 74.6, "y": 2.98 },
	{ "name": "light4", "parent": "root", "length": 73.85, "rotation": -98.13, "x": 162.14, "y": 496.42 },
	{ "name": "sv8", "parent": "light4", "length": 436.16, "rotation": -0.53, "x": 87.57, "y": -1.06 },
	{ "name": "light5", "parent": "root", "length": 68.97, "rotation": -128.85, "x": 421.75, "y": 399.44 },
	{ "name": "sv4", "parent": "light5", "length": 523.09, "rotation": 5.84, "x": 84.4, "y": -14.39 },
	{ "name": "light6", "parent": "root", "length": 83.7, "rotation": -120.47, "x": 709.25, "y": 346.58 },
	{ "name": "sv2", "parent": "light6", "length": 414.11, "rotation": 6.26, "x": 89.19, "y": 3.23 }
],
"slots": [
	{ "name": "pol4", "bone": "root", "attachment": "pol4" },
	{ "name": "pol3", "bone": "root", "attachment": "pol3" },
	{ "name": "pol2", "bone": "root", "attachment": "pol2" },
	{ "name": "pol1", "bone": "root", "attachment": "pol1" },
	{ "name": "sv8", "bone": "sv8", "attachment": "sv8" },
	{ "name": "light4", "bone": "light4", "attachment": "light4" },
	{ "name": "sv7", "bone": "sv7", "attachment": "sv7" },
	{ "name": "light3", "bone": "light3", "attachment": "light3" },
	{ "name": "sv6", "bone": "sv6", "attachment": "sv6" },
	{ "name": "light2", "bone": "light2", "attachment": "light2" },
	{ "name": "sv5", "bone": "sv5", "attachment": "sv5" },
	{ "name": "light1", "bone": "light1", "attachment": "light1" },
	{ "name": "sv4", "bone": "sv4", "attachment": "sv4" },
	{ "name": "light5", "bone": "light5", "attachment": "light5" },
	{ "name": "sv2", "bone": "sv2", "attachment": "sv2" },
	{ "name": "light6", "bone": "light6", "attachment": "light6" },
	{ "name": "sound2", "bone": "sound2", "attachment": "sound2" },
	{ "name": "sound1", "bone": "sound1", "attachment": "sound1" }
],
"skins": [
	{
		"name": "default",
		"attachments": {
			"light1": {
				"light1": { "x": 36.21, "y": 5.41, "rotation": 90, "width": 154, "height": 82 }
			},
			"light2": {
				"light2": { "x": 66.53, "y": 12.4, "rotation": 63.08, "width": 138, "height": 116 }
			},
			"light3": {
				"light3": { "x": 83.73, "y": 5.04, "rotation": 44.47, "width": 150, "height": 141 }
			},
			"light4": {
				"light4": { "x": 42.86, "y": -7.15, "rotation": 98.13, "width": 166, "height": 102 }
			},
			"light5": {
				"light5": { "x": 56.99, "y": -10.27, "rotation": 128.85, "width": 122, "height": 115 }
			},
			"light6": {
				"light6": { "x": 63.35, "y": -25.68, "rotation": 120.47, "width": 158, "height": 108 }
			},
			"pol1": {
				"pol1": { "x": -630.5, "y": -381.5, "width": 373, "height": 87 }
			},
			"pol2": {
				"pol2": { "x": -267.5, "y": -464.5, "width": 415, "height": 69 }
			},
			"pol3": {
				"pol3": { "x": 151, "y": -355, "width": 386, "height": 82 }
			},
			"pol4": {
				"pol4": { "x": 538, "y": -445, "width": 418, "height": 62 }
			},
			"sound1": {
				"sound1": { "x": 241.03, "y": -13.48, "rotation": -91.97, "width": 378, "height": 494 }
			},
			"sound2": {
				"sound2": { "x": 270.57, "y": 13.96, "rotation": -89.44, "width": 348, "height": 552 }
			},
			"sv2": {
				"sv2": {
					"type": "mesh",
					"uvs": [ 1, 0.01888, 0.45332, 0.98484, 0.33089, 1, 0.17774, 0.98491, 0, 0.88119, 0.94318, 0 ],
					"triangles": [ 0, 1, 4, 0, 4, 5, 2, 3, 4, 1, 2, 4 ],
					"vertices": [ -31.82, 13.32, 734.14, 102.24, 766.04, 59.4, 782.31, -4.82, 741.36, -106.24, -35, -14.65 ],
					"hull": 6,
					"edges": [ 0, 2, 4, 6, 6, 8, 10, 0, 2, 4, 8, 10 ],
					"width": 426,
					"height": 761
				}
			},
			"sv4": {
				"sv4": {
					"type": "mesh",
					"uvs": [ 1, 0.02594, 0.28075, 0.99988, 0.09651, 0.99979, 0, 0.94767, 0.97359, 0 ],
					"triangles": [ 1, 3, 4, 1, 2, 3, 4, 0, 1 ],
					"vertices": [ -3.58, 12.47, 856.59, 70.38, 915.14, -19.89, 912.06, -89.1, -11.99, -11.39 ],
					"hull": 5,
					"edges": [ 0, 2, 2, 4, 6, 8, 4, 6, 8, 0 ],
					"width": 584,
					"height": 773
				}
			},
			"sv5": {
				"sv5": {
					"type": "mesh",
					"uvs": [ 0.81546, 0.0013, 1, 0.97752, 0.37284, 1, 0, 0.97084, 0.63609, 0.01303, 0.80568, 3.6E-4 ],
					"triangles": [ 4, 5, 0, 1, 4, 0, 1, 3, 4, 2, 3, 1 ],
					"vertices": [ -24.67, 19.79, 887, 75.29, 910.79, -36.42, 885.18, -103.81, -12.91, -12.04, -25.51, 18.02 ],
					"hull": 6,
					"edges": [ 0, 10, 2, 4, 4, 6, 8, 10, 0, 2, 6, 8 ],
					"width": 179,
					"height": 935
				}
			},
			"sv6": {
				"sv6": {
					"type": "mesh",
					"uvs": [ 0.13204, 0.00553, 1, 0.94134, 0.01381, 0.99934, 0.00965, 0.01243 ],
					"triangles": [ 2, 3, 0, 2, 0, 1 ],
					"vertices": [ -8.29, 29.3, 725.56, 145.36, 666.32, -210.14, -15.84, -14.76 ],
					"hull": 4,
					"edges": [ 0, 2, 2, 4, 6, 0, 4, 6 ],
					"width": 363,
					"height": 719
				}
			},
			"sv7": {
				"sv7": {
					"type": "mesh",
					"uvs": [ 0.12086, 0, 1, 0.93191, 0.88852, 0.99307, 0.631, 1, 0, 0.0252 ],
					"triangles": [ 1, 3, 0, 2, 3, 1, 4, 0, 3 ],
					"vertices": [ -29.94, 32.67, 879.75, 102.17, 906, 30.89, 860.53, -86.97, -33.94, -30.29 ],
					"hull": 5,
					"edges": [ 0, 2, 4, 6, 2, 4, 8, 0, 6, 8 ],
					"width": 490,
					"height": 863
				}
			},
			"sv8": {
				"sv8": {
					"type": "mesh",
					"uvs": [ 0.99958, 0.00665, 0.70236, 0.99998, 0.25734, 0.99329, 0.00288, 0.9362, 0.81719, 0 ],
					"triangles": [ 3, 4, 0, 1, 3, 0, 1, 2, 3 ],
					"vertices": [ -6.53, 20.44, 850.83, 84.53, 859.93, -13.56, 819.69, -76.58, -6.13, -20.27 ],
					"hull": 5,
					"edges": [ 0, 8, 2, 4, 6, 8, 0, 2, 4, 6 ],
					"width": 221,
					"height": 863
				}
			}
		}
	}
],
"animations": {
	"animation": {
		"slots": {
			"pol1": {
				"attachment": [
					{ "name": null },
					{ "time": 1, "name": "pol1" },
					{ "time": 2.3333, "name": null },
					{ "time": 4.5333, "name": "pol1" },
					{ "time": 6.6667, "name": null }
				]
			},
			"pol2": {
				"attachment": [
					{ "time": 0.7, "name": null },
					{ "time": 2.9, "name": "pol2" },
					{ "time": 5.0333, "name": null },
					{ "time": 6.0333, "name": "pol2" }
				]
			},
			"pol3": {
				"attachment": [
					{ "time": 0.9667, "name": null },
					{ "time": 1.9667, "name": "pol3" },
					{ "time": 3.3, "name": null },
					{ "time": 5.5, "name": "pol3" }
				]
			},
			"pol4": {
				"attachment": [
					{ "time": 2.4667, "name": null },
					{ "time": 3.4667, "name": "pol4" },
					{ "time": 4.8, "name": null }
				]
			},
			"sv5": {
				"color": [
					{ "color": "ffffff58", "curve": 0.326, "c2": 0.31, "c3": 0.757 },
					{ "time": 0.2333, "color": "ffffffff", "curve": 0.25, "c3": 0.75 },
					{ "time": 0.4667, "color": "ffffff3a", "curve": 0.25, "c3": 0.75 },
					{ "time": 0.7333, "color": "ffffffff", "curve": 0.25, "c3": 0.75 },
					{ "time": 0.9667, "color": "ffffff3a", "curve": 0.25, "c3": 0.75 },
					{ "time": 1.2333, "color": "ffffffff", "curve": 0.25, "c3": 0.75 },
					{ "time": 1.4667, "color": "ffffff3a", "curve": 0.25, "c3": 0.75 },
					{ "time": 1.7333, "color": "ffffffff", "curve": 0.25, "c3": 0.75 },
					{ "time": 1.9667, "color": "ffffff3a", "curve": 0.25, "c3": 0.75 },
					{ "time": 2.2333, "color": "ffffffff", "curve": 0.25, "c3": 0.75 },
					{ "time": 2.4667, "color": "ffffff3a", "curve": 0.25, "c3": 0.75 },
					{ "time": 2.7333, "color": "ffffffff", "curve": 0.25, "c3": 0.75 },
					{ "time": 2.9667, "color": "ffffff3a", "curve": 0.25, "c3": 0.75 },
					{ "time": 3.2333, "color": "ffffffff", "curve": 0.25, "c3": 0.75 },
					{ "time": 3.4667, "color": "ffffff3a", "curve": 0.25, "c3": 0.75 },
					{ "time": 3.7333, "color": "ffffffff", "curve": 0.25, "c3": 0.75 },
					{ "time": 3.9667, "color": "ffffff3a", "curve": 0.25, "c3": 0.75 },
					{ "time": 4.2333, "color": "ffffffff", "curve": 0.25, "c3": 0.75 },
					{ "time": 4.4667, "color": "ffffff3a", "curve": 0.25, "c3": 0.75 },
					{ "time": 4.7333, "color": "ffffffff", "curve": 0.25, "c3": 0.75 },
					{ "time": 4.9667, "color": "ffffff3a", "curve": 0.25, "c3": 0.75 },
					{ "time": 5.2333, "color": "ffffffff", "curve": 0.25, "c3": 0.75 },
					{ "time": 5.4667, "color": "ffffff3a", "curve": 0.25, "c3": 0.75 },
					{ "time": 5.7333, "color": "ffffffff", "curve": 0.25, "c3": 0.75 },
					{ "time": 6.0333, "color": "ffffff3a", "curve": 0.25, "c3": 0.75 },
					{ "time": 6.3333, "color": "ffffffff", "curve": 0.25, "c3": 0.75 },
					{ "time": 6.6, "color": "ffffff3a", "curve": 0.28, "c3": 0.623, "c4": 0.39 },
					{ "time": 6.6667, "color": "ffffff58" }
				]
			},
			"sv8": {
				"color": [
					{ "color": "ffffffff", "curve": 0.25, "c3": 0.75 },
					{ "time": 0.2333, "color": "ffffff3a", "curve": 0.25, "c3": 0.75 },
					{ "time": 0.5, "color": "ffffffff", "curve": 0.25, "c3": 0.75 },
					{ "time": 0.7333, "color": "ffffff3a", "curve": 0.25, "c3": 0.75 },
					{ "time": 1, "color": "ffffffff", "curve": 0.25, "c3": 0.75 },
					{ "time": 1.2333, "color": "ffffff3a", "curve": 0.25, "c3": 0.75 },
					{ "time": 1.5, "color": "ffffffff", "curve": 0.25, "c3": 0.75 },
					{ "time": 1.7333, "color": "ffffff3a", "curve": 0.25, "c3": 0.75 },
					{ "time": 2, "color": "ffffffff", "curve": 0.25, "c3": 0.75 },
					{ "time": 2.2333, "color": "ffffff3a", "curve": 0.25, "c3": 0.75 },
					{ "time": 2.5, "color": "ffffffff", "curve": 0.25, "c3": 0.75 },
					{ "time": 2.7333, "color": "ffffff3a", "curve": 0.25, "c3": 0.75 },
					{ "time": 3, "color": "ffffffff", "curve": 0.25, "c3": 0.75 },
					{ "time": 3.2333, "color": "ffffff3a", "curve": 0.25, "c3": 0.75 },
					{ "time": 3.5, "color": "ffffffff", "curve": 0.25, "c3": 0.75 },
					{ "time": 3.7333, "color": "ffffff3a", "curve": 0.25, "c3": 0.75 },
					{ "time": 4, "color": "ffffffff", "curve": 0.25, "c3": 0.75 },
					{ "time": 4.2333, "color": "ffffff3a", "curve": 0.25, "c3": 0.75 },
					{ "time": 4.5, "color": "ffffffff", "curve": 0.25, "c3": 0.75 },
					{ "time": 4.7333, "color": "ffffff3a", "curve": 0.25, "c3": 0.75 },
					{ "time": 5, "color": "ffffffff", "curve": 0.25, "c3": 0.75 },
					{ "time": 5.2333, "color": "ffffff3a", "curve": 0.25, "c3": 0.75 },
					{ "time": 5.5, "color": "ffffffff", "curve": 0.25, "c3": 0.75 },
					{ "time": 5.8, "color": "ffffff3a", "curve": 0.25, "c3": 0.75 },
					{ "time": 6.1, "color": "ffffffff", "curve": 0.25, "c3": 0.75 },
					{ "time": 6.3667, "color": "ffffff3a", "curve": 0.25, "c3": 0.75 },
					{ "time": 6.6667, "color": "ffffffff" }
				]
			}
		},
		"bones": {
			"sound1": {
				"scale": [
					{ "curve": 0.25, "c3": 0.75 },
					{ "time": 0.1333, "x": 0.98, "y": 1.02, "curve": 0.25, "c3": 0.75 },
					{ "time": 0.2667, "curve": 0.25, "c3": 0.75 },
					{ "time": 0.4, "x": 0.98, "y": 1.02, "curve": 0.25, "c3": 0.75 },
					{ "time": 0.5667, "curve": 0.25, "c3": 0.75 },
					{ "time": 0.7, "x": 0.98, "y": 1.02, "curve": 0.25, "c3": 0.75 },
					{ "time": 0.8333, "curve": 0.25, "c3": 0.75 },
					{ "time": 0.9667, "x": 0.98, "y": 1.02, "curve": 0.25, "c3": 0.75 },
					{ "time": 1.1, "curve": 0.25, "c3": 0.75 },
					{ "time": 1.2333, "x": 0.98, "y": 1.02, "curve": 0.25, "c3": 0.75 },
					{ "time": 1.4, "curve": 0.25, "c3": 0.75 },
					{ "time": 1.5333, "x": 0.98, "y": 1.02, "curve": 0.25, "c3": 0.75 },
					{ "time": 1.6667, "curve": 0.25, "c3": 0.75 },
					{ "time": 1.8, "x": 0.98, "y": 1.02, "curve": 0.25, "c3": 0.75 },
					{ "time": 1.9333, "curve": 0.25, "c3": 0.75 },
					{ "time": 2.0667, "x": 0.98, "y": 1.02, "curve": 0.25, "c3": 0.75 },
					{ "time": 2.2333, "curve": 0.25, "c3": 0.75 },
					{ "time": 2.3667, "x": 0.98, "y": 1.02, "curve": 0.25, "c3": 0.75 },
					{ "time": 2.5, "curve": 0.25, "c3": 0.75 },
					{ "time": 2.6333, "x": 0.98, "y": 1.02, "curve": 0.25, "c3": 0.75 },
					{ "time": 2.7667, "curve": 0.25, "c3": 0.75 },
					{ "time": 2.9, "x": 0.98, "y": 1.02, "curve": 0.25, "c3": 0.75 },
					{ "time": 3.0667, "curve": 0.25, "c3": 0.75 },
					{ "time": 3.2, "x": 0.98, "y": 1.02, "curve": 0.25, "c3": 0.75 },
					{ "time": 3.3333, "curve": 0.25, "c3": 0.75 },
					{ "time": 3.4667, "x": 0.98, "y": 1.02, "curve": 0.25, "c3": 0.75 },
					{ "time": 3.6, "curve": 0.25, "c3": 0.75 },
					{ "time": 3.7333, "x": 0.98, "y": 1.02, "curve": 0.25, "c3": 0.75 },
					{ "time": 3.9, "curve": 0.25, "c3": 0.75 },
					{ "time": 4.0333, "x": 0.98, "y": 1.02, "curve": 0.25, "c3": 0.75 },
					{ "time": 4.1667, "curve": 0.25, "c3": 0.75 },
					{ "time": 4.3, "x": 0.98, "y": 1.02, "curve": 0.25, "c3": 0.75 },
					{ "time": 4.4333, "curve": 0.25, "c3": 0.75 },
					{ "time": 4.5667, "x": 0.98, "y": 1.02, "curve": 0.25, "c3": 0.75 },
					{ "time": 4.7, "curve": 0.25, "c3": 0.75 },
					{ "time": 4.8667, "x": 0.98, "y": 1.02, "curve": 0.25, "c3": 0.75 },
					{ "time": 5, "curve": 0.25, "c3": 0.75 },
					{ "time": 5.1333, "x": 0.98, "y": 1.02, "curve": 0.25, "c3": 0.75 },
					{ "time": 5.2667, "curve": 0.25, "c3": 0.75 },
					{ "time": 5.4, "x": 0.98, "y": 1.02, "curve": 0.25, "c3": 0.75 },
					{ "time": 5.5333, "curve": 0.25, "c3": 0.75 },
					{ "time": 5.7, "x": 0.98, "y": 1.02, "curve": 0.25, "c3": 0.75 },
					{ "time": 5.8333, "curve": 0.25, "c3": 0.75 },
					{ "time": 5.9667, "x": 0.98, "y": 1.02, "curve": 0.25, "c3": 0.75 },
					{ "time": 6.1, "curve": 0.25, "c3": 0.75 },
					{ "time": 6.2333, "x": 0.98, "y": 1.02, "curve": 0.25, "c3": 0.75 },
					{ "time": 6.3667, "curve": 0.25, "c3": 0.75 },
					{ "time": 6.5333, "x": 0.98, "y": 1.02, "curve": 0.25, "c3": 0.75 },
					{ "time": 6.6667 }
				],
				"shear": [
					{ "curve": 0.25, "c3": 0.75 },
					{ "time": 0.4, "x": 1.2, "curve": 0.25, "c3": 0.75 },
					{ "time": 0.9667, "x": -1.2, "curve": 0.25, "c3": 0.75 },
					{ "time": 1.5333, "x": 1.2, "curve": 0.25, "c3": 0.75 },
					{ "time": 1.9333, "x": -1.2, "curve": 0.25, "c3": 0.75 },
					{ "time": 2.3667, "curve": 0.25, "c3": 0.75 },
					{ "time": 2.6333, "x": -1.2, "curve": 0.25, "c3": 0.75 },
					{ "time": 3.3333, "curve": 0.25, "c3": 0.75 },
					{ "time": 3.7333, "x": 1.2, "curve": 0.25, "c3": 0.75 },
					{ "time": 4.3, "x": -1.2, "curve": 0.25, "c3": 0.75 },
					{ "time": 4.8667, "x": 1.2, "curve": 0.25, "c3": 0.75 },
					{ "time": 5.2667, "x": -1.2, "curve": 0.25, "c3": 0.75 },
					{ "time": 5.7, "curve": 0.25, "c3": 0.75 },
					{ "time": 5.9667, "x": -1.2, "curve": 0.25, "c3": 0.75 },
					{ "time": 6.6667 }
				]
			},
			"sound2": {
				"scale": [
					{ "x": 0.99, "y": 1.01, "curve": 0.375, "c2": 0.5, "c3": 0.75 },
					{ "time": 0.0667, "curve": 0.25, "c3": 0.75 },
					{ "time": 0.2, "x": 0.98, "y": 1.02, "curve": 0.25, "c3": 0.75 },
					{ "time": 0.3333, "curve": 0.25, "c3": 0.75 },
					{ "time": 0.5, "x": 0.98, "y": 1.02, "curve": 0.25, "c3": 0.75 },
					{ "time": 0.6333, "curve": 0.25, "c3": 0.75 },
					{ "time": 0.7667, "x": 0.98, "y": 1.02, "curve": 0.25, "c3": 0.75 },
					{ "time": 0.9, "curve": 0.25, "c3": 0.75 },
					{ "time": 1.0333, "x": 0.98, "y": 1.02, "curve": 0.25, "c3": 0.75 },
					{ "time": 1.1667, "curve": 0.25, "c3": 0.75 },
					{ "time": 1.3333, "x": 0.98, "y": 1.02, "curve": 0.25, "c3": 0.75 },
					{ "time": 1.4667, "curve": 0.25, "c3": 0.75 },
					{ "time": 1.6, "x": 0.98, "y": 1.02, "curve": 0.25, "c3": 0.75 },
					{ "time": 1.7333, "curve": 0.25, "c3": 0.75 },
					{ "time": 1.8667, "x": 0.98, "y": 1.02, "curve": 0.25, "c3": 0.75 },
					{ "time": 2, "curve": 0.25, "c3": 0.75 },
					{ "time": 2.1667, "x": 0.98, "y": 1.02, "curve": 0.25, "c3": 0.75 },
					{ "time": 2.3, "curve": 0.25, "c3": 0.75 },
					{ "time": 2.4333, "x": 0.98, "y": 1.02, "curve": 0.25, "c3": 0.75 },
					{ "time": 2.5667, "curve": 0.25, "c3": 0.75 },
					{ "time": 2.7, "x": 0.98, "y": 1.02, "curve": 0.25, "c3": 0.75 },
					{ "time": 2.8333, "curve": 0.25, "c3": 0.75 },
					{ "time": 2.9667, "x": 0.98, "y": 1.02, "curve": 0.25, "c3": 0.75 },
					{ "time": 3.1333, "curve": 0.25, "c3": 0.75 },
					{ "time": 3.2667, "x": 0.98, "y": 1.02, "curve": 0.25, "c3": 0.625, "c4": 0.5 },
					{ "time": 3.3333, "x": 0.99, "y": 1.01, "curve": 0.375, "c2": 0.5, "c3": 0.75 },
					{ "time": 3.4, "curve": 0.25, "c3": 0.75 },
					{ "time": 3.5333, "x": 0.98, "y": 1.02, "curve": 0.25, "c3": 0.75 },
					{ "time": 3.6667, "curve": 0.25, "c3": 0.75 },
					{ "time": 3.8, "x": 0.98, "y": 1.02, "curve": 0.25, "c3": 0.75 },
					{ "time": 3.9667, "curve": 0.25, "c3": 0.75 },
					{ "time": 4.1, "x": 0.98, "y": 1.02, "curve": 0.25, "c3": 0.75 },
					{ "time": 4.2333, "curve": 0.25, "c3": 0.75 },
					{ "time": 4.3667, "x": 0.98, "y": 1.02, "curve": 0.25, "c3": 0.75 },
					{ "time": 4.5, "curve": 0.25, "c3": 0.75 },
					{ "time": 4.6333, "x": 0.98, "y": 1.02, "curve": 0.25, "c3": 0.75 },
					{ "time": 4.8, "curve": 0.25, "c3": 0.75 },
					{ "time": 4.9333, "x": 0.98, "y": 1.02, "curve": 0.25, "c3": 0.75 },
					{ "time": 5.0667, "curve": 0.25, "c3": 0.75 },
					{ "time": 5.2, "x": 0.98, "y": 1.02, "curve": 0.25, "c3": 0.75 },
					{ "time": 5.3333, "curve": 0.25, "c3": 0.75 },
					{ "time": 5.4667, "x": 0.98, "y": 1.02, "curve": 0.25, "c3": 0.75 },
					{ "time": 5.6333, "curve": 0.25, "c3": 0.75 },
					{ "time": 5.7667, "x": 0.98, "y": 1.02, "curve": 0.25, "c3": 0.75 },
					{ "time": 5.9, "curve": 0.25, "c3": 0.75 },
					{ "time": 6.0333, "x": 0.98, "y": 1.02, "curve": 0.25, "c3": 0.75 },
					{ "time": 6.1667, "curve": 0.25, "c3": 0.75 },
					{ "time": 6.3, "x": 0.98, "y": 1.02, "curve": 0.25, "c3": 0.75 },
					{ "time": 6.4667, "curve": 0.25, "c3": 0.75 },
					{ "time": 6.6, "x": 0.98, "y": 1.02, "curve": 0.25, "c3": 0.625, "c4": 0.5 },
					{ "time": 6.6667, "x": 0.99, "y": 1.01 }
				],
				"shear": [
					{ "x": -0.97, "curve": 0.371, "c2": 0.62, "c3": 0.71 },
					{ "time": 0.0667, "x": -1.2, "curve": 0.25, "c3": 0.75 },
					{ "time": 0.5, "curve": 0.25, "c3": 0.75 },
					{ "time": 0.7667, "x": -1.2, "curve": 0.25, "c3": 0.75 },
					{ "time": 1.4667, "curve": 0.25, "c3": 0.75 },
					{ "time": 1.8667, "x": 1.2, "curve": 0.25, "c3": 0.75 },
					{ "time": 2.4333, "x": -1.2, "curve": 0.25, "c3": 0.75 },
					{ "time": 2.9667, "x": 1.2, "curve": 0.243, "c3": 0.689, "c4": 0.75 },
					{ "time": 3.3333, "x": -0.97, "curve": 0.371, "c2": 0.62, "c3": 0.71 },
					{ "time": 3.4, "x": -1.2, "curve": 0.25, "c3": 0.75 },
					{ "time": 3.8, "curve": 0.25, "c3": 0.75 },
					{ "time": 4.1, "x": -1.2, "curve": 0.25, "c3": 0.75 },
					{ "time": 4.8, "curve": 0.25, "c3": 0.75 },
					{ "time": 5.2, "x": 1.2, "curve": 0.25, "c3": 0.75 },
					{ "time": 5.7667, "x": -1.2, "curve": 0.25, "c3": 0.75 },
					{ "time": 6.3, "x": 1.2, "curve": 0.243, "c3": 0.689, "c4": 0.75 },
					{ "time": 6.6667, "x": -0.97 }
				]
			},
			"light2": {
				"rotate": [
					{ "curve": 0.25, "c3": 0.75 },
					{ "time": 3.3, "angle": 12.74, "curve": 0.25, "c3": 0.75 },
					{ "time": 6.6667 }
				]
			},
			"sv6": {
				"rotate": [
					{ "curve": 0.25, "c3": 0.75 },
					{ "time": 3.7, "angle": 10.13, "curve": 0.25, "c3": 0.75 },
					{ "time": 6.6667 }
				]
			},
			"light6": {
				"rotate": [
					{ "angle": -1.1, "curve": 0.333, "c2": 0.33, "c3": 0.758 },
					{ "time": 2, "angle": -5.97, "curve": 0.25, "c3": 0.75 },
					{ "time": 6, "curve": 0.276, "c3": 0.621, "c4": 0.4 },
					{ "time": 6.6667, "angle": -1.1 }
				]
			},
			"sv2": {
				"rotate": [
					{ "curve": 0.25, "c3": 0.75 },
					{ "time": 3.1667, "angle": -2.89, "curve": 0.25, "c3": 0.75 },
					{ "time": 6.6667 }
				]
			},
			"sv8": {
				"rotate": [
					{ "curve": 0.25, "c3": 0.75 },
					{ "time": 1.1667, "angle": -8.5, "curve": 0.25, "c3": 0.75 },
					{ "time": 2.2333, "angle": 4.99, "curve": 0.25, "c3": 0.75 },
					{ "time": 3.3333, "angle": -11.06, "curve": 0.248, "c3": 0.738, "c4": 0.94 },
					{ "time": 4.4667, "angle": 0.57, "curve": 0.25, "c3": 0.75 },
					{ "time": 5.5, "angle": -6.07, "curve": 0.25, "c3": 0.75 },
					{ "time": 6.6667 }
				]
			},
			"sv5": {
				"rotate": [
					{ "angle": 1.64, "curve": 0.376, "c2": 0.61, "c3": 0.717 },
					{ "time": 0.2333, "curve": 0.25, "c3": 0.75 },
					{ "time": 1.3333, "angle": 11.57, "curve": 0.25, "c3": 0.75 },
					{ "time": 2.4333, "angle": 0.32, "curve": 0.25, "c3": 0.75 },
					{ "time": 3.6, "angle": 10.21, "curve": 0.25, "c3": 0.75 },
					{ "time": 4.6667, "angle": -0.13, "curve": 0.25, "c3": 0.75 },
					{ "time": 5.7667, "angle": 12.05, "curve": 0.243, "c3": 0.678, "c4": 0.71 },
					{ "time": 6.6667, "angle": 1.64 }
				]
			},
			"light3": {
				"rotate": [
					{ "angle": -0.5, "curve": 0.308, "c2": 0.24, "c3": 0.757 },
					{ "time": 2.6667, "angle": -5.6, "curve": 0.25, "c3": 0.75 },
					{ "time": 6.1667, "curve": 0.292, "c3": 0.63, "c4": 0.37 },
					{ "time": 6.6667, "angle": -0.5 }
				]
			},
			"sv7": {
				"rotate": [
					{ "curve": 0.25, "c3": 0.75 },
					{ "time": 3.1667, "angle": -2.39, "curve": 0.25, "c3": 0.75 },
					{ "time": 6.6667 }
				]
			},
			"light5": {
				"rotate": [
					{},
					{ "time": 3.6333, "angle": 1.97 },
					{ "time": 6.6667 }
				]
			},
			"sv4": {
				"rotate": [
					{ "curve": 0.25, "c3": 0.75 },
					{ "time": 3.6333, "angle": 4.21, "curve": 0.25, "c3": 0.75 },
					{ "time": 6.6667 }
				]
			}
		},
		"deform": {
			"default": {
				"sv2": {
					"sv2": [
						{ "curve": 0.25, "c3": 0.75 },
						{
							"time": 3.1667,
							"offset": 2,
							"vertices": [ -7.88837, 50.85565, 34.43353, -12.21194, 40.48297, -44.80649, 87.44263, -80.65967 ],
							"curve": 0.25,
							"c3": 0.75
						},
						{ "time": 6.6667 }
					]
				},
				"sv4": {
					"sv4": [
						{ "curve": 0.25, "c3": 0.75 },
						{
							"time": 3.6333,
							"offset": 2,
							"vertices": [ -70.80072, 155.25467, -60.37527, 129.54456, -25.78278, 5.03044 ],
							"curve": 0.25,
							"c3": 0.75
						},
						{ "time": 6.6667 }
					]
				},
				"sv5": {
					"sv5": [
						{
							"offset": 2,
							"vertices": [ -3.30027, 14.63289, -0.02928, 1.54088, -1.43439, -5.63243 ]
						},
						{ "time": 0.2333 },
						{
							"time": 2.4333,
							"offset": 2,
							"vertices": [ -15.08923, 88.23584, -0.56042, 29.4968, -27.45831, -107.82071 ]
						},
						{
							"time": 4.6667,
							"offset": 2,
							"vertices": [ -31.58826, 140.05756, -0.28021, 14.7484, -13.72916, -53.91035 ]
						},
						{
							"time": 6.6667,
							"offset": 2,
							"vertices": [ -3.30027, 14.63289, -0.02928, 1.54088, -1.43439, -5.63243 ]
						}
					]
				},
				"sv6": {
					"sv6": [
						{ "curve": 0.25, "c3": 0.75 },
						{
							"time": 3.7,
							"offset": 2,
							"vertices": [ 345.5431, 62.75089, 58.70026, -54.04907 ],
							"curve": 0.25,
							"c3": 0.75
						},
						{ "time": 6.6667 }
					]
				},
				"sv7": {
					"sv7": [
						{ "curve": 0.25, "c3": 0.75 },
						{
							"time": 3.1667,
							"offset": 2,
							"vertices": [ -36.72791, -50.92111, -42.92026, -82.61746, -56.1655, -90.01462 ],
							"curve": 0.25,
							"c3": 0.75
						},
						{ "time": 6.6667 }
					]
				},
				"sv8": {
					"sv8": [
						{},
						{
							"time": 1.1667,
							"offset": 2,
							"vertices": [ -14.58414, -7.31059, 8.70474, -28.18861, 38.13596, -78.04661 ]
						},
						{
							"time": 2.2333,
							"offset": 2,
							"vertices": [ -1.36202, 83.46192, 23.8635, 7.92146, 6.8933, -110.1276 ]
						},
						{
							"time": 3.3333,
							"offset": 2,
							"vertices": [ -41.84113, 105.10719, 12.3249, 29.58381, 46.25386, -22.50284 ]
						},
						{
							"time": 4.4667,
							"offset": 2,
							"vertices": [ -57.1152, 181.6638, -16.12652, 37.74995, 16.10387, -27.73631 ]
						},
						{
							"time": 5.5,
							"offset": 2,
							"vertices": [ -57.16507, 166.91864, 13.98871, 92.50093, 8.53993, -14.70865 ]
						},
						{ "time": 6.6667 }
					]
				}
			}
		}
	}
}
}